{
	"games" :
	[{
			"id" : "1",
			"home" : {
				"id" : "1",
				"name" : "Brazil",
				"flag" : "http://upload.wikimedia.org/wikipedia/en/thumb/0/05/Flag_of_Brazil.svg/22px-Flag_of_Brazil.svg.png"
			},
			"away" : {
				"id" : "2",
				"name" : "Croatia",
				"flag" : "http://upload.wikimedia.org/wikipedia/commons/thumb/1/1b/Flag_of_Croatia.svg/23px-Flag_of_Croatia.svg.png"
			},
			"time" : "",
			"stage" : "",
			"index" : 0
		}, 
		{
			"id" : "1",
			"home" : {
				"id" : "1",
				"name" : "Brazil",
				"flag" : "http://upload.wikimedia.org/wikipedia/en/thumb/0/05/Flag_of_Brazil.svg/22px-Flag_of_Brazil.svg.png"
			},
			"away" : {
				"id" : "2",
				"name" : "Croatia",
				"flag" : "http://upload.wikimedia.org/wikipedia/commons/thumb/1/1b/Flag_of_Croatia.svg/23px-Flag_of_Croatia.svg.png"
			},
			"time" : "",
			"stage" : "",
			"index" : 0
		}, 
		{
			"id" : "1",
			"home" : {
				"id" : "1",
				"name" : "Brazil",
				"flag" : "http://upload.wikimedia.org/wikipedia/en/thumb/0/05/Flag_of_Brazil.svg/22px-Flag_of_Brazil.svg.png"
			},
			"away" : {
				"id" : "2",
				"name" : "Croatia",
				"flag" : "http://upload.wikimedia.org/wikipedia/commons/thumb/1/1b/Flag_of_Croatia.svg/23px-Flag_of_Croatia.svg.png"
			},
			"time" : "",
			"stage" : "",
			"index" : 0
		}, 
		{
			"id" : "1",
			"home" : {
				"id" : "1",
				"name" : "Brazil",
				"flag" : "http://upload.wikimedia.org/wikipedia/en/thumb/0/05/Flag_of_Brazil.svg/22px-Flag_of_Brazil.svg.png"
			},
			"away" : {
				"id" : "2",
				"name" : "Croatia",
				"flag" : "http://upload.wikimedia.org/wikipedia/commons/thumb/1/1b/Flag_of_Croatia.svg/23px-Flag_of_Croatia.svg.png"
			},
			"time" : "",
			"stage" : "",
			"index" : 0
		}, 
		{
			"id" : "1",
			"home" : {
				"id" : "1",
				"name" : "Brazil",
				"flag" : "http://upload.wikimedia.org/wikipedia/en/thumb/0/05/Flag_of_Brazil.svg/22px-Flag_of_Brazil.svg.png"
			},
			"away" : {
				"id" : "2",
				"name" : "Croatia",
				"flag" : "http://upload.wikimedia.org/wikipedia/commons/thumb/1/1b/Flag_of_Croatia.svg/23px-Flag_of_Croatia.svg.png"
			},
			"time" : "",
			"stage" : "",
			"index" : 0
		}, 
		{
			"id" : "1",
			"home" : {
				"id" : "1",
				"name" : "Brazil",
				"flag" : "http://upload.wikimedia.org/wikipedia/en/thumb/0/05/Flag_of_Brazil.svg/22px-Flag_of_Brazil.svg.png"
			},
			"away" : {
				"id" : "2",
				"name" : "Croatia",
				"flag" : "http://upload.wikimedia.org/wikipedia/commons/thumb/1/1b/Flag_of_Croatia.svg/23px-Flag_of_Croatia.svg.png"
			},
			"time" : "",
			"stage" : "",
			"index" : 0
		}, 
		{
			"id" : "1",
			"home" : {
				"id" : "1",
				"name" : "Brazil",
				"flag" : "http://upload.wikimedia.org/wikipedia/en/thumb/0/05/Flag_of_Brazil.svg/22px-Flag_of_Brazil.svg.png"
			},
			"away" : {
				"id" : "2",
				"name" : "Croatia",
				"flag" : "http://upload.wikimedia.org/wikipedia/commons/thumb/1/1b/Flag_of_Croatia.svg/23px-Flag_of_Croatia.svg.png"
			},
			"time" : "",
			"stage" : "",
			"index" : 0
		}
		
		, 
		{
			"id" : "1",
			"home" : {
				"id" : "1",
				"name" : "Brazil",
				"flag" : "http://upload.wikimedia.org/wikipedia/en/thumb/0/05/Flag_of_Brazil.svg/22px-Flag_of_Brazil.svg.png"
			},
			"away" : {
				"id" : "2",
				"name" : "Croatia",
				"flag" : "http://upload.wikimedia.org/wikipedia/commons/thumb/1/1b/Flag_of_Croatia.svg/23px-Flag_of_Croatia.svg.png"
			},
			"time" : "",
			"stage" : "",
			"index" : 0
		}
		
		
		
	]

}
